decodanda/__init__.py
decodanda/classes.py
decodanda/imports.py
decodanda/in_time.py
decodanda/utilities.py
decodanda/visualize.py
decodanda-0.7.3.dist-info/LICENSE.md
decodanda-0.7.3.dist-info/METADATA
decodanda-0.7.3.dist-info/WHEEL
decodanda-0.7.3.dist-info/top_level.txt
decodanda-0.7.3.dist-info/RECORD
